neo4j_semantic_search/__init__.py
neo4j_semantic_search/config.py
neo4j_semantic_search/semantic_search.py
neo4j_semantic_search/server.py
neo4j_semantic_search_mcp-0.1.0.dist-info/METADATA
neo4j_semantic_search_mcp-0.1.0.dist-info/WHEEL
neo4j_semantic_search_mcp-0.1.0.dist-info/entry_points.txt
neo4j_semantic_search_mcp-0.1.0.dist-info/top_level.txt
neo4j_semantic_search_mcp-0.1.0.dist-info/RECORD
