Metadata-Version: 2.4
Name: neo4j-semantic-search-mcp
Version: 0.1.0
Summary: MCP server for semantic search in Neo4j knowledge graphs
Requires-Python: >=3.13
Requires-Dist: mcp>=1.20.0
Requires-Dist: neo4j>=6.0.2
Requires-Dist: openai>=2.7.1
Requires-Dist: pydantic>=2.12.4
